isstringtool/__init__.py
isstringtool/__main__.py
isstringtool-0.1.0.dist-info/METADATA
isstringtool-0.1.0.dist-info/WHEEL
isstringtool-0.1.0.dist-info/entry_points.txt
isstringtool-0.1.0.dist-info/top_level.txt
isstringtool-0.1.0.dist-info/RECORD
