Metadata-Version: 2.4
Name: isstringtool
Version: 0.1.0
Summary: check if my input is string or not
Requires-Python: >=3.8
